.DS_Store
PiView_AG/CPU.py
PiView_AG/GPU.py
PiView_AG/Hardware.py
PiView_AG/Host.py
PiView_AG/Network.py
PiView_AG/Storage.py
PiView_AG/Utils.py
PiView_AG/__init__.py
tests/__init__.py
tests/test_CPU.py
tests/test_Utils_format_bytes.py
tests/test_Utils_line_draw.py
PiView_AG-1.0.1.dist-info/LICENSE.txt
PiView_AG-1.0.1.dist-info/METADATA
PiView_AG-1.0.1.dist-info/WHEEL
PiView_AG-1.0.1.dist-info/top_level.txt
PiView_AG-1.0.1.dist-info/RECORD
