Metadata-Version: 2.1
Name: PiView-AG
Version: 1.0.1
Summary: A Raspberry Pi system information package
Home-page: https://github.com/AdyGCode/PiView-AG
Author: Adrian Gould
Author-email: adrian.gould@nmtafe.wa.edu.au
Maintainer: Adrian Gould
Maintainer-email: adrian.gould@nmtafe.wa.edu.au
License: UNKNOWN
Platform: UNKNOWN
Classifier: Programming Language :: Python :: 3
Classifier: License :: OSI Approved :: Open Software License 3.0 (OSL-3.0)
Classifier: Operating System :: OS Independent
Requires-Python: >=3.6
Requires-Dist: datetime
Requires-Dist: os
Requires-Dist: platform
Requires-Dist: psutil
Requires-Dist: pytest
Requires-Dist: random
Requires-Dist: socket
Requires-Dist: subprocess
